{
"meta":{"test_sets":[],"test_metrics":[],"learn_metrics":[{"best_value":"Min","name":"RMSE"}],"launch_mode":"Train","parameters":"","iteration_count":100,"learn_sets":["learn"],"name":"experiment"},
"iterations":[
{"learn":[14.005006],"iteration":0,"passed_time":0.003341055596,"remaining_time":0.330764504},
{"learn":[13.14441192],"iteration":1,"passed_time":0.006326653078,"remaining_time":0.3100060008},
{"learn":[12.34258257],"iteration":2,"passed_time":0.009336708673,"remaining_time":0.3018869138},
{"learn":[11.64527793],"iteration":3,"passed_time":0.01185161284,"remaining_time":0.2844387081},
{"learn":[11.02766183],"iteration":4,"passed_time":0.01491695152,"remaining_time":0.2834220789},
{"learn":[10.43485794],"iteration":5,"passed_time":0.01785443824,"remaining_time":0.2797195325},
{"learn":[9.890641275],"iteration":6,"passed_time":0.02084182045,"remaining_time":0.2768984718},
{"learn":[9.492161212],"iteration":7,"passed_time":0.02394092857,"remaining_time":0.2753206786},
{"learn":[9.105082953],"iteration":8,"passed_time":0.02690646877,"remaining_time":0.2720542953},
{"learn":[8.674157135],"iteration":9,"passed_time":0.02880782584,"remaining_time":0.2592704326},
{"learn":[8.341743544],"iteration":10,"passed_time":0.03059886282,"remaining_time":0.2475726173},
{"learn":[8.049372916],"iteration":11,"passed_time":0.0324047675,"remaining_time":0.2376349617},
{"learn":[7.757318612],"iteration":12,"passed_time":0.03408843008,"remaining_time":0.2281302629},
{"learn":[7.522206899],"iteration":13,"passed_time":0.03588554983,"remaining_time":0.2204398061},
{"learn":[7.297756655],"iteration":14,"passed_time":0.03766694794,"remaining_time":0.2134460383},
{"learn":[7.088359431],"iteration":15,"passed_time":0.03941852373,"remaining_time":0.2069472496},
{"learn":[6.882113791],"iteration":16,"passed_time":0.04120008561,"remaining_time":0.2011533591},
{"learn":[6.704728832],"iteration":17,"passed_time":0.04298022538,"remaining_time":0.1957988045},
{"learn":[6.563881962],"iteration":18,"passed_time":0.04470261387,"remaining_time":0.1905743012},
{"learn":[6.418790279],"iteration":19,"passed_time":0.0464731198,"remaining_time":0.1858924792},
{"learn":[6.315756953],"iteration":20,"passed_time":0.04818883227,"remaining_time":0.1812817976},
{"learn":[6.210157751],"iteration":21,"passed_time":0.04996346078,"remaining_time":0.1771431791},
{"learn":[6.115058449],"iteration":22,"passed_time":0.05172161232,"remaining_time":0.173154963},
{"learn":[6.014819884],"iteration":23,"passed_time":0.05347431777,"remaining_time":0.1693353396},
{"learn":[5.93117229],"iteration":24,"passed_time":0.05528058759,"remaining_time":0.1658417628},
{"learn":[5.844857622],"iteration":25,"passed_time":0.0568088536,"remaining_time":0.1616867372},
{"learn":[5.771145213],"iteration":26,"passed_time":0.0582091323,"remaining_time":0.1573802466},
{"learn":[5.704018229],"iteration":27,"passed_time":0.05961728685,"remaining_time":0.1533015948},
{"learn":[5.665806474],"iteration":28,"passed_time":0.06103571028,"remaining_time":0.1494322562},
{"learn":[5.616500369],"iteration":29,"passed_time":0.06252184971,"remaining_time":0.145884316},
{"learn":[5.558023666],"iteration":30,"passed_time":0.06393283176,"remaining_time":0.1423021094},
{"learn":[5.510080976],"iteration":31,"passed_time":0.06536765361,"remaining_time":0.1389062639},
{"learn":[5.468747792],"iteration":32,"passed_time":0.06675628814,"remaining_time":0.1355354941},
{"learn":[5.429275534],"iteration":33,"passed_time":0.06818866518,"remaining_time":0.1323662324},
{"learn":[5.402117324],"iteration":34,"passed_time":0.0696468322,"remaining_time":0.1293441169},
{"learn":[5.367635151],"iteration":35,"passed_time":0.07107817985,"remaining_time":0.1263612086},
{"learn":[5.345181232],"iteration":36,"passed_time":0.07251587432,"remaining_time":0.1234729752},
{"learn":[5.319151269],"iteration":37,"passed_time":0.07390874339,"remaining_time":0.1205879497},
{"learn":[5.296134146],"iteration":38,"passed_time":0.07535243039,"remaining_time":0.1178589296},
{"learn":[5.269629003],"iteration":39,"passed_time":0.07672185403,"remaining_time":0.1150827811},
{"learn":[5.251147059],"iteration":40,"passed_time":0.07810046534,"remaining_time":0.1123884745},
{"learn":[5.248003302],"iteration":41,"passed_time":0.07866917326,"remaining_time":0.1086383821},
{"learn":[5.232376509],"iteration":42,"passed_time":0.08005529613,"remaining_time":0.1061198112},
{"learn":[5.213524255],"iteration":43,"passed_time":0.08147207854,"remaining_time":0.1036917363},
{"learn":[5.189691584],"iteration":44,"passed_time":0.0828739665,"remaining_time":0.1012904035},
{"learn":[5.166052198],"iteration":45,"passed_time":0.08448355331,"remaining_time":0.09917634519},
{"learn":[5.140406659],"iteration":46,"passed_time":0.08608962498,"remaining_time":0.09707978987},
{"learn":[5.118929684],"iteration":47,"passed_time":0.08754710685,"remaining_time":0.09484269908},
{"learn":[5.108792602],"iteration":48,"passed_time":0.08899425802,"remaining_time":0.09262667672},
{"learn":[5.098141225],"iteration":49,"passed_time":0.09043009757,"remaining_time":0.09043009757},
{"learn":[5.085926393],"iteration":50,"passed_time":0.09183631366,"remaining_time":0.0882348896},
{"learn":[5.067816804],"iteration":51,"passed_time":0.09321106809,"remaining_time":0.08604098593},
{"learn":[5.049834901],"iteration":52,"passed_time":0.09463958324,"remaining_time":0.08392566816},
{"learn":[5.03838627],"iteration":53,"passed_time":0.09601841012,"remaining_time":0.08179346047},
{"learn":[5.033534248],"iteration":54,"passed_time":0.0969262479,"remaining_time":0.07930329374},
{"learn":[5.023726885],"iteration":55,"passed_time":0.09835085437,"remaining_time":0.07727567129},
{"learn":[5.01290392],"iteration":56,"passed_time":0.09978020172,"remaining_time":0.07527278376},
{"learn":[5.005569127],"iteration":57,"passed_time":0.1011630843,"remaining_time":0.0732560266},
{"learn":[4.989969032],"iteration":58,"passed_time":0.1026590281,"remaining_time":0.0713393246},
{"learn":[4.976762446],"iteration":59,"passed_time":0.1040448652,"remaining_time":0.06936324347},
{"learn":[4.967222715],"iteration":60,"passed_time":0.1054964932,"remaining_time":0.06744857764},
{"learn":[4.954407599],"iteration":61,"passed_time":0.1069474161,"remaining_time":0.0655484163},
{"learn":[4.942125056],"iteration":62,"passed_time":0.1083427166,"remaining_time":0.06362984942},
{"learn":[4.930230716],"iteration":63,"passed_time":0.1098287441,"remaining_time":0.06177866853},
{"learn":[4.921695642],"iteration":64,"passed_time":0.1112634272,"remaining_time":0.05991107619},
{"learn":[4.906405625],"iteration":65,"passed_time":0.1126626698,"remaining_time":0.05803834506},
{"learn":[4.894330248],"iteration":66,"passed_time":0.1140859712,"remaining_time":0.05619159774},
{"learn":[4.88211557],"iteration":67,"passed_time":0.1154383948,"remaining_time":0.05432395049},
{"learn":[4.877946398],"iteration":68,"passed_time":0.1168801032,"remaining_time":0.05251135072},
{"learn":[4.863182126],"iteration":69,"passed_time":0.1182637629,"remaining_time":0.05068446981},
{"learn":[4.84646533],"iteration":70,"passed_time":0.1197209724,"remaining_time":0.04890011548},
{"learn":[4.838014752],"iteration":71,"passed_time":0.1211653846,"remaining_time":0.0471198718},
{"learn":[4.82981137],"iteration":72,"passed_time":0.122574109,"remaining_time":0.04533562937},
{"learn":[4.817094767],"iteration":73,"passed_time":0.1239975407,"remaining_time":0.04356670349},
{"learn":[4.808314151],"iteration":74,"passed_time":0.1253735234,"remaining_time":0.04179117447},
{"learn":[4.796235023],"iteration":75,"passed_time":0.1270664773,"remaining_time":0.04012625598},
{"learn":[4.784434534],"iteration":76,"passed_time":0.12879487,"remaining_time":0.03847119493},
{"learn":[4.774402487],"iteration":77,"passed_time":0.1305037051,"remaining_time":0.03680873733},
{"learn":[4.76731896],"iteration":78,"passed_time":0.131978715,"remaining_time":0.03508294957},
{"learn":[4.75934113],"iteration":79,"passed_time":0.1334043943,"remaining_time":0.03335109858},
{"learn":[4.754106378],"iteration":80,"passed_time":0.1348414638,"remaining_time":0.03162947917},
{"learn":[4.744002932],"iteration":81,"passed_time":0.1362840212,"remaining_time":0.02991600464},
{"learn":[4.731700554],"iteration":82,"passed_time":0.1376408915,"remaining_time":0.02819150791},
{"learn":[4.723284153],"iteration":83,"passed_time":0.1389861428,"remaining_time":0.02647355102},
{"learn":[4.712232782],"iteration":84,"passed_time":0.1404514358,"remaining_time":0.0247855475},
{"learn":[4.703046867],"iteration":85,"passed_time":0.1419171328,"remaining_time":0.02310278906},
{"learn":[4.698601855],"iteration":86,"passed_time":0.1433133674,"remaining_time":0.02141464111},
{"learn":[4.692429407],"iteration":87,"passed_time":0.1447483514,"remaining_time":0.01973841155},
{"learn":[4.675027364],"iteration":88,"passed_time":0.1461627675,"remaining_time":0.01806506115},
{"learn":[4.662368584],"iteration":89,"passed_time":0.1475735708,"remaining_time":0.01639706342},
{"learn":[4.646206172],"iteration":90,"passed_time":0.1489160815,"remaining_time":0.0147279641},
{"learn":[4.641245848],"iteration":91,"passed_time":0.1503291741,"remaining_time":0.01307210209},
{"learn":[4.633900435],"iteration":92,"passed_time":0.1517398386,"remaining_time":0.01142127818},
{"learn":[4.624738236],"iteration":93,"passed_time":0.1531565525,"remaining_time":0.009775950161},
{"learn":[4.612798287],"iteration":94,"passed_time":0.1551473824,"remaining_time":0.008165651706},
{"learn":[4.605222001],"iteration":95,"passed_time":0.1565717766,"remaining_time":0.006523824027},
{"learn":[4.601725912],"iteration":96,"passed_time":0.1579844615,"remaining_time":0.004886117367},
{"learn":[4.59722371],"iteration":97,"passed_time":0.1593833917,"remaining_time":0.003252722279},
{"learn":[4.580235665],"iteration":98,"passed_time":0.1608114773,"remaining_time":0.001624358357},
{"learn":[4.57591791],"iteration":99,"passed_time":0.1621945805,"remaining_time":0}
]}